visier_platform_sdk/__init__.py
visier_platform_sdk/api_client.py
visier_platform_sdk/api_response.py
visier_platform_sdk/configuration.py
visier_platform_sdk/exceptions.py
visier_platform_sdk/py.typed
visier_platform_sdk/rest.py
visier_platform_sdk/api/__init__.py
visier_platform_sdk/api/analytic_objects_v2_api.py
visier_platform_sdk/api/basic_authentication_api.py
visier_platform_sdk/api/benchmarks_api.py
visier_platform_sdk/api/concepts_v2_api.py
visier_platform_sdk/api/consolidated_analytics_api.py
visier_platform_sdk/api/data_and_job_handling_api.py
visier_platform_sdk/api/data_intake_api.py
visier_platform_sdk/api/data_model_api.py
visier_platform_sdk/api/data_query_api.py
visier_platform_sdk/api/data_upload_api.py
visier_platform_sdk/api/data_version_export_api.py
visier_platform_sdk/api/dimensions_api.py
visier_platform_sdk/api/dimensions_v2_api.py
visier_platform_sdk/api/direct_data_intake_api.py
visier_platform_sdk/api/email_domains_api.py
visier_platform_sdk/api/encryption_keys_api.py
visier_platform_sdk/api/metrics_v2_api.py
visier_platform_sdk/api/network_subnets_api.py
visier_platform_sdk/api/o_auth2_api.py
visier_platform_sdk/api/object_configuration_api.py
visier_platform_sdk/api/permissions_api.py
visier_platform_sdk/api/personalized_alerts_api.py
visier_platform_sdk/api/pgp_keys_api.py
visier_platform_sdk/api/plan_administration_api.py
visier_platform_sdk/api/plan_data_load_api.py
visier_platform_sdk/api/production_versions_api.py
visier_platform_sdk/api/profiles_api.py
visier_platform_sdk/api/projects_api.py
visier_platform_sdk/api/release_version_configuration_api.py
visier_platform_sdk/api/reporting_api.py
visier_platform_sdk/api/search_api.py
visier_platform_sdk/api/sidecar_solutions_api.py
visier_platform_sdk/api/source_files_download_api.py
visier_platform_sdk/api/sources_api.py
visier_platform_sdk/api/system_status_api.py
visier_platform_sdk/api/table_source_api.py
visier_platform_sdk/api/tenants_v1_api.py
visier_platform_sdk-22222222.99201.2518.dist-info/METADATA
visier_platform_sdk-22222222.99201.2518.dist-info/WHEEL
visier_platform_sdk-22222222.99201.2518.dist-info/top_level.txt
visier_platform_sdk-22222222.99201.2518.dist-info/RECORD
