Metadata-Version: 2.4
Name: visier-platform-sdk
Version: 22222222.99201.2518
Summary: API Reference
Home-page: https://github.com/visier/python-sdk
Author: Visier
Author-email: alpine@visier.com
License: Apache License, Version 2.0
Keywords: Visier,Visier-SDK,API Reference
Requires-Dist: urllib3<2; platform_python_implementation == "PyPy"
Requires-Dist: urllib3<3.0.0,>=2.1.0; platform_python_implementation != "PyPy"
Requires-Dist: python-dateutil>=2.8.2
Requires-Dist: Flask>=3.0.0
Requires-Dist: pydantic>=2
Requires-Dist: typing-extensions>=4.7.1
Dynamic: author
Dynamic: author-email
Dynamic: description
Dynamic: description-content-type
Dynamic: home-page
Dynamic: keywords
Dynamic: license
Dynamic: requires-dist
Dynamic: summary
